encrypterlib_rewrite/__init__.py
encrypterlib_rewrite-1.1.dist-info/METADATA
encrypterlib_rewrite-1.1.dist-info/WHEEL
encrypterlib_rewrite-1.1.dist-info/top_level.txt
encrypterlib_rewrite-1.1.dist-info/RECORD
