Metadata-Version: 2.1
Name: encrypterlib-rewrite
Version: 1.1
Summary: An easy-to-use encryption package.
Home-page: UNKNOWN
Author: Coder436
Author-email: <codergd@gmail.com>
License: UNKNOWN
Keywords: cryptography,asymmetric encryption,symmetric encryption,openssl
Platform: UNKNOWN
Classifier: Development Status :: 4 - Beta
Classifier: Intended Audience :: Developers
Classifier: Programming Language :: Python :: 3
Classifier: Operating System :: Unix
Classifier: Operating System :: MacOS :: MacOS X
Classifier: Operating System :: Microsoft :: Windows
Requires-Dist: cryptography
